setup.py
Adafruit_Seesaw/__init__.py
Adafruit_Seesaw/seesaw.py
Adafruit_seesaw.egg-info/PKG-INFO
Adafruit_seesaw.egg-info/SOURCES.txt
Adafruit_seesaw.egg-info/dependency_links.txt
Adafruit_seesaw.egg-info/requires.txt
Adafruit_seesaw.egg-info/top_level.txt