Metadata-Version: 1.1
Name: Adafruit-seesaw
Version: 1.0
Summary: Python library to use the seesaw helper IC with raspberry pi or other linux boards.
Home-page: https://github.com/adafruit/Adafruit_Python_seesaw
Author: Dean Miller
Author-email: dean@adafruit.com
License: MIT
Platform: UNKNOWN
Classifier: Development Status :: 4 - Beta
Classifier: Operating System :: POSIX :: Linux
Classifier: License :: OSI Approved :: MIT License
Classifier: Intended Audience :: Developers
Classifier: Programming Language :: Python :: 2.7
Classifier: Programming Language :: Python :: 3
Classifier: Topic :: Software Development
Classifier: Topic :: System :: Hardware
